itk_dreg/__init__.py
itk_dreg/itk.py
itk_dreg/register.py
itk_dreg/base/__init__.py
itk_dreg/base/image_block_interface.py
itk_dreg/base/itk_typing.py
itk_dreg/base/registration_interface.py
itk_dreg/block/__init__.py
itk_dreg/block/convert.py
itk_dreg/block/dask.py
itk_dreg/block/image.py
itk_dreg/elastix/__init__.py
itk_dreg/elastix/register.py
itk_dreg/elastix/serialize.py
itk_dreg/elastix/util.py
itk_dreg/reduce_dfield/__init__.py
itk_dreg/reduce_dfield/dreg.py
itk_dreg/reduce_dfield/matrix_transform.py
itk_dreg/reduce_dfield/transform.py
itk_dreg/reduce_dfield/transform_collection.py
itk_dreg-0.0.1.dist-info/LICENSE
itk_dreg-0.0.1.dist-info/WHEEL
itk_dreg-0.0.1.dist-info/METADATA
itk_dreg-0.0.1.dist-info/RECORD
