Metadata-Version: 2.1
Name: itk_dreg
Version: 0.0.1
Summary: ITK-DREG Distributed registration framework.
Keywords: ITK,InsightToolkit
Author-email: InsightSoftwareConsortium <matt.mccormick@kitware.com>
Requires-Python: >=3.9
Classifier: License :: OSI Approved :: Apache Software License
Classifier: Programming Language :: Python
Classifier: Programming Language :: C++
Classifier: Development Status :: 4 - Beta
Classifier: Intended Audience :: Developers
Classifier: Intended Audience :: Education
Classifier: Intended Audience :: Healthcare Industry
Classifier: Intended Audience :: Science/Research
Classifier: Topic :: Scientific/Engineering
Classifier: Topic :: Scientific/Engineering :: Medical Science Apps.
Classifier: Topic :: Scientific/Engineering :: Information Analysis
Classifier: Topic :: Software Development :: Libraries
Classifier: Operating System :: Android
Classifier: Operating System :: Microsoft :: Windows
Classifier: Operating System :: POSIX
Classifier: Operating System :: Unix
Classifier: Operating System :: MacOS
Requires-Dist: dask[distributed] >=2023.10.0
Requires-Dist: itk >=5.4rc02
Requires-Dist: numpy
Requires-Dist: black ; extra == "dev"
Requires-Dist: pytest ; extra == "dev"
Requires-Dist: itk-elastix>=0.19.0 ; extra == "impl"
Requires-Dist: scipy>=1.11.3 ; extra == "impl"
Requires-Dist: aind_ccf_alignment_experiments ; extra == "lightsheet"
Requires-Dist: s3fs ; extra == "lightsheet"
Requires-Dist: zarr ; extra == "lightsheet"
Requires-Dist: matplotlib ; extra == "notebook"
Requires-Dist: itkwidgets>=0.32.0 ; extra == "notebook"
Requires-Dist: graphviz ; extra == "notebook"
Requires-Dist: itk-elastix>=0.19.1 ; extra == "test"
Requires-Dist: itk-ioomezarrngff>=0.2.1 ; extra == "test"
Requires-Dist: nbmake ; extra == "test"
Requires-Dist: pytest ; extra == "test"
Requires-Dist: scipy>=1.11.3 ; extra == "test"
Project-URL: Home, https://github.com/InsightSoftwareConsortium/itk-dreg
Provides-Extra: dev
Provides-Extra: impl
Provides-Extra: lightsheet
Provides-Extra: notebook
Provides-Extra: test
